ionize/Solvent.py
ionize/__init__.py
ionize/__main__.py
ionize/__version__.py
ionize/constants.py
ionize/deserialize.py
ionize/serialize.py
ionize/tests.py
ionize/Database/__init__.py
ionize/Database/ion_data.json
ionize/Ion/BaseIon.py
ionize/Ion/__init__.py
ionize/Ion/acidity.py
ionize/Ion/fixed_state.py
ionize/Ion/ionization.py
ionize/Ion/mobility.py
ionize/Ion/transport.py
ionize/IonComplex/IonComplex.py
ionize/IonComplex/Protein.py
ionize/IonComplex/__init__.py
ionize/PolyIon/NucleicAcid.py
ionize/PolyIon/Peptide.py
ionize/PolyIon/PolyIon.py
ionize/PolyIon/__init__.py
ionize/Solution/__init__.py
ionize/Solution/conductivity.py
ionize/Solution/conservation.py
ionize/Solution/debye.py
ionize/Solution/equilibrium.py
ionize/Solution/titrate.py
ionize/Solution/transference.py
ionize-1.5.3.dist-info/LICENSE
ionize-1.5.3.dist-info/METADATA
ionize-1.5.3.dist-info/WHEEL
ionize-1.5.3.dist-info/entry_points.txt
ionize-1.5.3.dist-info/top_level.txt
ionize-1.5.3.dist-info/RECORD
