Metadata-Version: 2.1
Name: ionize
Version: 1.5.3
Summary: A package for calculating electrolyte properties.
Home-page: http://lewisamarshall.github.io/ionize/
Author: Lewis A. Marshall
Author-email: lewis.a.marshall@gmail.com
License: LICENSE
Classifier: Programming Language :: Python
Classifier: Development Status :: 3 - Alpha
Classifier: Environment :: Console
Classifier: Intended Audience :: Science/Research
Classifier: Operating System :: OS Independent
Classifier: Topic :: Software Development :: Libraries :: Python Modules
Classifier: Topic :: Scientific/Engineering :: Chemistry
Requires: numpy
Requires: scipy
Requires: biopython
Requires: click
License-File: LICENSE
Requires-Dist: numpy
Requires-Dist: scipy
Requires-Dist: pandas
Requires-Dist: biopython
Requires-Dist: click
